{
    "tasks": [
      {
        "name": "купить хлеб и дальше очень длинный текст который должен превратиться в точки",
        "id": 1
        "name": "Убраться на кухне длинный длинный текст превратить в точки2122",
        "id": 5
      },
      {
        "name": "купить молоко и дальше очень длинный текст который должен превратиться в точки",
        "id": 2
        "name": "Создать программу №5 длинный длинный текст превратить в точки",
        "id": 7
      },
      {
        "name": "убраться в комнате и дальше очень длинный текст который должен превратиться в точки",
        "id": 4
        "name": "1212 ",
        "id": 8
      },
      {
        "name": "убраться на кухне и дальше очень длинный текст который должен превратиться в точки",
        "id": 5
        "name": "23232",
        "id": 9
      },
      {
        "name": "2323232323",
        "id": 10
      },
      {
        "name": "1212 и дальше очень длинный текст который должен превратиться в точки",
        "id": 6
        "name": "23232323232323",
        "id": 11
      }
    ]
  }